tessera_client
